{
  "type": "AdaptiveCard",
  "body": [
    {
      "type": "TextBlock",
      "size": "extraLarge",
      "weight": "Bolder",
      "text": "{Title2}",
      "wrap": true
    },
    {
      "type": "ColumnSet",
      "columns": [
        {
          "type": "Column",
          "items": [
            {
              "type": "TextBlock",
              "weight": "Bolder",
              "text": "John",
              "wrap": true
            },
            {
              "type": "TextBlock",
              "spacing": "None",
              "text": "Created {DateCreated}",
              "isSubtle": true,
              "wrap": true
            }
          ],
          "width": "auto"
        }
      ]
    },
    {
      "type": "TextBlock",
      "text": "{FirstParagraph}",
      "wrap": true
    }
  ],
  "actions": [
    {
      "type": "Action.OpenUrl",
      "title": "View",
      "url": "https://adaptivecards.io"
    },
    {
      "type": "Action.OpenUrl",
      "title": "Download as PNG",
      "url": "https://weather.com"
    }
  ],
  "$schema": "http://adaptivecards.io/schemas/adaptive-card.json",
  "version": "1.0"
}